fs/__init__.py
fs/fileSystem.py
python_fs-0.1.dist-info/LICENSE
python_fs-0.1.dist-info/METADATA
python_fs-0.1.dist-info/WHEEL
python_fs-0.1.dist-info/top_level.txt
python_fs-0.1.dist-info/RECORD
